whatsapp_linkcraft/__init__.py
whatsapp_linkcraft/main.py
whatsapp_linkcraft/prompts.py
whatsapp_linkcraft-2025.12.21183621.dist-info/METADATA
whatsapp_linkcraft-2025.12.21183621.dist-info/WHEEL
whatsapp_linkcraft-2025.12.21183621.dist-info/top_level.txt
whatsapp_linkcraft-2025.12.21183621.dist-info/RECORD
