Metadata-Version: 2.4
Name: whatsapp-linkcraft
Version: 2025.12.21183621
Summary: whatsapp-linkcraft generates validated WhatsApp chat links from phone numbers using an LLM, handling formatting and errors automatically for clickable URLs.
Author-email: whatsapp-linkcraft <hi@eugene.plus>
License: MIT
Project-URL: Homepage, https://github.com/chigwell/whatsapp-linkcraft
Requires-Python: >=3.9
Requires-Dist: langchain-llm7>=0.0.0
Requires-Dist: llmatch-messages>=0.0.0
Requires-Dist: langchain-core>=0.3.0
